{
  "generated_at": "2026-04-05T07:25:41.860323-06:00",
  "leader_count": 3,
  "leaders": [
    {
      "actual_dte": 8,
      "ask": 1.92,
      "bid": 1.7,
      "candidate_id": "XSP-2026-04-13-PUT-628",
      "delta": -0.1406,
      "expiration": "2026-04-13",
      "expiry_fallback": true,
      "expiry_note": "No exact 7DTE expiry available; using nearest valid expiry 2026-04-13.",
      "fallback": false,
      "label": "8DTE (requested 7DTE, fallback)",
      "last_price": 2.33,
      "mid_price": 1.81,
      "option_type": "put",
      "requested_dte": 7,
      "spread_ratio": 0.1215,
      "strategy": "Credit Spread Sell",
      "strike": 628.0,
      "symbol": "XSP",
      "underlying_price": 658.27,
      "vix": 23.87
    },
    {
      "actual_dte": 8,
      "ask": 0.65,
      "bid": 0.59,
      "candidate_id": "IWM-2026-04-13-CALL-262",
      "delta": 0.1407,
      "expiration": "2026-04-13",
      "expiry_fallback": true,
      "expiry_note": "No exact 7DTE expiry available; using nearest valid expiry 2026-04-13.",
      "fallback": false,
      "label": "8DTE (requested 7DTE, fallback)",
      "last_price": 0.71,
      "mid_price": 0.62,
      "option_type": "call",
      "requested_dte": 7,
      "spread_ratio": 0.0968,
      "strategy": "Credit Spread Sell",
      "strike": 262.0,
      "symbol": "IWM",
      "underlying_price": 251.29,
      "vix": 23.87
    },
    {
      "actual_dte": 8,
      "ask": 1.94,
      "bid": 1.91,
      "candidate_id": "SPY-2026-04-13-PUT-627",
      "delta": -0.1393,
      "expiration": "2026-04-13",
      "expiry_fallback": true,
      "expiry_note": "No exact 7DTE expiry available; using nearest valid expiry 2026-04-13.",
      "fallback": false,
      "label": "8DTE (requested 7DTE, fallback)",
      "last_price": 1.98,
      "mid_price": 1.925,
      "option_type": "put",
      "requested_dte": 7,
      "spread_ratio": 0.015600000000000001,
      "strategy": "Credit Spread Sell",
      "strike": 627.0,
      "symbol": "SPY",
      "underlying_price": 655.83,
      "vix": 23.87
    }
  ],
  "run_id": "20260405T072541-0600",
  "ticket_count": 8
}
